funcron/__init__.py
funcron/center/__init__.py
funcron/center/app.py
funcron/center/models.py
funcron/center/common/__init__.py
funcron/center/common/database.py
funcron/center/common/functions.py
funcron/center/common/config/__init__.py
funcron/center/common/config/config.py
funcron/center/common/scheduler/CuBackgroundScheduler.py
funcron/center/common/scheduler/CuGeventScheduler.py
funcron/center/common/scheduler/__init__.py
funcron/center/pages/__init__.py
funcron/center/pages/decorated.py
funcron/center/pages/api/__init__.py
funcron/center/pages/api/core.py
funcron/center/pages/api/views.py
funcron/center/pages/crons/__init__.py
funcron/center/pages/crons/core.py
funcron/center/pages/main/__init__.py
funcron/center/pages/main/core.py
funcron/center/pages/main/errors.py
funcron/center/pages/main/views.py
funcron/center/static/__init__.py
funcron/center/static/jquery.js
funcron/center/static/vue.js
funcron/center/static/images/__init__.py
funcron/center/static/images/mini_code.png
funcron/center/static/js/__init__.py
funcron/center/static/js/ajaxForm.js
funcron/center/static/js/common.js
funcron/center/static/js/jquery.js
funcron/center/static/js/md5.js
funcron/center/static/js/qrcode.min.js
funcron/center/static/js/requests.js
funcron/center/static/js/signs.js
funcron/center/static/js/wind.js
funcron/center/static/js/artDialog/__init__.py
funcron/center/static/js/artDialog/artDialog.extend.js
funcron/center/static/js/artDialog/artDialog.js
funcron/center/static/js/artDialog/iframeTools.js
funcron/center/static/js/artDialog/skins/__init__.py
funcron/center/static/js/artDialog/skins/blue.css
funcron/center/static/js/artDialog/skins/default.css
funcron/center/static/js/artDialog/skins/blue/__init__.py
funcron/center/static/js/artDialog/skins/blue/bg.png
funcron/center/static/js/artDialog/skins/blue/bg2.png
funcron/center/static/js/artDialog/skins/blue/bg_css3.png
funcron/center/static/js/artDialog/skins/blue/bg_css3_2.png
funcron-202308211945.dist-info/LICENSE
funcron-202308211945.dist-info/METADATA
funcron-202308211945.dist-info/WHEEL
funcron-202308211945.dist-info/entry_points.txt
funcron-202308211945.dist-info/top_level.txt
funcron-202308211945.dist-info/RECORD
