Metadata-Version: 2.1
Name: funcron
Version: 202308211945
Summary: funcron
Home-page: https://github.com/1007530194
Author: bingtao
Author-email: 1007530194@qq.com
License-File: LICENSE
Requires-Dist: supervisor
Requires-Dist: apscheduler
Requires-Dist: gunicorn
Requires-Dist: records
Requires-Dist: gevent
